vektonn/__init__.py
vektonn/async_client.py
vektonn/client.py
vektonn/dtos.py
vektonn/errors.py
vektonn/service_endpoints.py
vektonn/utils.py
vektonn-0.7.1.dist-info/LICENSE
vektonn-0.7.1.dist-info/METADATA
vektonn-0.7.1.dist-info/WHEEL
vektonn-0.7.1.dist-info/top_level.txt
vektonn-0.7.1.dist-info/zip-safe
vektonn-0.7.1.dist-info/RECORD
