Metadata-Version: 2.1
Name: vektonn
Version: 0.7.1
Summary: Python client for Vektonn
Home-page: https://github.com/vektonn/vektonn-client-python
Maintainer: Vektonn Team
Maintainer-email: team@vektonn.io
License: Apache License 2.0
Platform: UNKNOWN
Classifier: Development Status :: 5 - Production/Stable
Classifier: Intended Audience :: Developers
Classifier: License :: OSI Approved :: Apache Software License
Classifier: Operating System :: OS Independent
Classifier: Programming Language :: Python
Classifier: Programming Language :: Python :: 3
Classifier: Programming Language :: Python :: 3.7
Classifier: Programming Language :: Python :: 3.8
Classifier: Programming Language :: Python :: 3.9
Classifier: Programming Language :: Python :: 3.10
Requires-Python: >=3.7
License-File: LICENSE
Requires-Dist: aiohttp (~=3.8.1)
Requires-Dist: orjson (~=3.6.5)
Requires-Dist: pydantic (~=1.9.0)
Requires-Dist: requests (~=2.27.1)
